gbopyrator/__init__.py
gbopyrator/__main__.py
gbopyrator/cartridge_utils.py
gbopyrator/coms_utils.py
gbopyrator/constants.py
gbopyrator/gb_gbc_roms_info.json
gbopyrator/gbopyrator.py
gbopyrator/printer.py
gbopyrator-0.5.dist-info/METADATA
gbopyrator-0.5.dist-info/WHEEL
gbopyrator-0.5.dist-info/entry_points.txt
gbopyrator-0.5.dist-info/top_level.txt
gbopyrator-0.5.dist-info/RECORD
