Metadata-Version: 2.1
Name: gbopyrator
Version: 0.5
Home-page: https://github.com/N0ciple/gbopyrator
Classifier: Development Status :: 4 - Beta
Classifier: Intended Audience :: Developers
Classifier: License :: OSI Approved :: MIT License
Classifier: Programming Language :: Python :: 3
Classifier: Programming Language :: Python :: 3.7
Classifier: Programming Language :: Python :: 3.8
Classifier: Programming Language :: Python :: 3.9
Requires-Python: >=3.7
Requires-Dist: rich (>=13.0.0)
Requires-Dist: pyusb (>=1.2.1)
Requires-Dist: crccheck (>=1.3.0)
Requires-Dist: setuptools
